<?xml version="1.0" encoding="UTF-8"?><index key="268436905">
<marker id="1432920079"/>
<marker id="1432920115"/>
<marker id="1432920116"/>
<marker id="1432920117"/>
<marker id="1432920118"/>
<marker id="1432920119"/>
<marker id="1432920123"/>
<marker id="1432920124"/>
<marker id="1432920125"/>
<marker id="1432920126"/>
<marker id="1432920127"/>
<marker id="1432920128"/>
<marker id="1432920129"/>
<marker id="1432920130"/>
<marker id="1432920131"/>
<marker id="1432920132"/>
<marker id="1432920133"/>
<marker id="1432920134"/>
<marker id="1432920137"/>
<marker id="1432920138"/>
<marker id="1432920139"/>
<marker id="1432920140"/>
<marker id="1432985633"/>
</index>
