<?xml version="1.0" encoding="UTF-8"?><index key="1879501772">
<marker id="1358110724"/>
<marker id="1358110726"/>
<marker id="1358110728"/>
<marker id="1358110729"/>
<marker id="1358110731"/>
<marker id="1358110733"/>
<marker id="1358110734"/>
<marker id="1358110735"/>
<marker id="1358110736"/>
<marker id="1358110737"/>
<marker id="1358110738"/>
<marker id="1358110739"/>
<marker id="1358110740"/>
<marker id="1358110743"/>
<marker id="1358110744"/>
<marker id="1358110745"/>
<marker id="1358110746"/>
<marker id="1358110747"/>
<marker id="1358110748"/>
<marker id="1358110749"/>
<marker id="1358110750"/>
<marker id="1358110751"/>
<marker id="1358110752"/>
<marker id="1358110753"/>
<marker id="1358110754"/>
<marker id="1358110755"/>
<marker id="1358110756"/>
<marker id="1358110757"/>
<marker id="1358110758"/>
<marker id="1358110759"/>
<marker id="1358110760"/>
<marker id="1358110761"/>
<marker id="1358110763"/>
<marker id="1358110764"/>
<marker id="1358110765"/>
<marker id="1358110766"/>
<marker id="1358110767"/>
<marker id="1358110768"/>
<marker id="1358110769"/>
</index>
