<?xml version="1.0" encoding="UTF-8"?><index key="1879475844">
<marker id="1610313745"/>
<marker id="1610313746"/>
<marker id="1610313749"/>
<marker id="1610313750"/>
<marker id="1610313751"/>
<marker id="1610313752"/>
<marker id="1610313753"/>
<marker id="1610313754"/>
<marker id="1610313755"/>
<marker id="1610313760"/>
<marker id="1610313761"/>
<marker id="1610313763"/>
<marker id="1610313765"/>
<marker id="1610313768"/>
<marker id="1610313776"/>
<marker id="1610313778"/>
<marker id="1610313779"/>
</index>
